vaultprojectkeyring/__init__.py
vaultprojectkeyring/secretbackend.py
vaultprojectkeyring/vaultbackend.py
keyring_vault_backend-1.3.0.dist-info/METADATA
keyring_vault_backend-1.3.0.dist-info/WHEEL
keyring_vault_backend-1.3.0.dist-info/entry_points.txt
keyring_vault_backend-1.3.0.dist-info/top_level.txt
keyring_vault_backend-1.3.0.dist-info/RECORD
