Metadata-Version: 2.1
Name: keyring-vault-backend
Version: 1.3.0
Summary: Hashicorp vault backend for python-keyring
Home-page: https://github.com/pschmitt/keyring-vault-backend
Author: Philipp Schmitt
Author-email: philipp.schmitt@post.lu
License: UNKNOWN
Platform: UNKNOWN
Requires-Dist: hvac
Requires-Dist: keyring
Requires-Dist: requests
